neo_data_svc/__init__.py
neo_data_svc/cache.py
neo_data_svc/core.py
neo_data_svc/rdms.py
neo_data_svc/repo.py
neo_data_svc/common/__init__.py
neo_data_svc/common/job.py
neo_data_svc/common/log.py
neo_data_svc/common/system.py
neo_data_svc-13.0.0.dist-info/METADATA
neo_data_svc-13.0.0.dist-info/WHEEL
neo_data_svc-13.0.0.dist-info/RECORD
