Metadata-Version: 2.4
Name: neo-data-svc
Version: 13.0.0
Summary: Data container
Author-email: Eric <xiaoxiang.cn@gmail.com>
License: Proprietary
Requires-Python: >=3.12.0
Requires-Dist: aiosqlite==0.21.0
Requires-Dist: apscheduler==3.11.0
Requires-Dist: asyncpg==0.30.0
Requires-Dist: click-completion==0.5.2
Requires-Dist: delta-spark==3.3.1
Requires-Dist: dynaconf==3.2.12
Requires-Dist: fastapi[standard]==0.115.12
Requires-Dist: httpx==0.28.1
Requires-Dist: lakefs==0.12.0
Requires-Dist: psycopg2-binary==2.9.10
Requires-Dist: pydantic-settings==2.10.1
Requires-Dist: pyspark==3.5.5
Requires-Dist: redis==6.4.0
Requires-Dist: slowapi==0.1.9
Requires-Dist: sqlalchemy==2.0.43
Requires-Dist: sqlmodel==0.0.27
Requires-Dist: typer==0.20.0
